line/__init__.py
linecode-1.0.0.dist-info/METADATA
linecode-1.0.0.dist-info/WHEEL
linecode-1.0.0.dist-info/top_level.txt
linecode-1.0.0.dist-info/RECORD
