Metadata-Version: 2.4
Name: linecode
Version: 1.0.0
Summary: A simple python based language.It can be embedded in python projects
Home-page: https://github.com/xystudio889/pyplus
Author: xystudio
Author-email: 173288240@qq.com
License: MIT
Requires-Python: >=3.6,<=3.14
Requires-Dist: toml
Dynamic: author
Dynamic: author-email
Dynamic: home-page
Dynamic: license
Dynamic: requires-dist
Dynamic: requires-python
Dynamic: summary
